.coveragerc
CHANGES.rst
LICENSE.GPL
LICENSE.txt
MANIFEST.in
README.rst
bootstrap.py
buildout.cfg
setup.py
collective/__init__.py
collective.simplewiki.egg-info/PKG-INFO
collective.simplewiki.egg-info/SOURCES.txt
collective.simplewiki.egg-info/dependency_links.txt
collective.simplewiki.egg-info/entry_points.txt
collective.simplewiki.egg-info/namespace_packages.txt
collective.simplewiki.egg-info/not-zip-safe
collective.simplewiki.egg-info/requires.txt
collective.simplewiki.egg-info/top_level.txt
collective/simplewiki/__init__.py
collective/simplewiki/configure.zcml
collective/simplewiki/filter.py
collective/simplewiki/interfaces.py
collective/simplewiki/testing.py
collective/simplewiki/transform.py
collective/simplewiki/profiles/default/browserlayer.xml
collective/simplewiki/tests/__init__.py
collective/simplewiki/tests/test_filter.py