Metadata-Version: 1.1
Name: collective.simplewiki
Version: 1.0.0
Summary: Simple wiki linking syntax support for Plone
Home-page: https://github.com/collective/collective.simplewiki
Author: Nathan Van Gheem
Author-email: vangheem@gmail.com
License: GPL
Keywords: Plone wiki wicked
Platform: UNKNOWN
Classifier: Programming Language :: Python
Classifier: Programming Language :: Python :: 2.7
Classifier: Framework :: Plone
Classifier: Framework :: Plone :: 5.0
Classifier: Framework :: Plone :: 5.1
